peaks/__init__.py
peaks/_lazy_import.py
peaks/ML/__init__.py
peaks/ML/clustering.py
peaks/ML/denoise.py
peaks/SARPES/__init__.py
peaks/bz/__init__.py
peaks/bz/plotting.py
peaks/bz/utils.py
peaks/core/__init__.py
peaks/core/options.py
peaks/core/GUI/__init__.py
peaks/core/GUI/GUI_utils/CircularListWidget.py
peaks/core/GUI/GUI_utils/Crosshair.py
peaks/core/GUI/GUI_utils/KeyPressGraphicsLayoutWidget.py
peaks/core/GUI/GUI_utils/__init__.py
peaks/core/GUI/GUI_utils/cursor_stats.py
peaks/core/GUI/disp_panels/__init__.py
peaks/core/GUI/disp_panels/degrid_panel.py
peaks/core/GUI/disp_panels/disp.py
peaks/core/GUI/disp_panels/disp_2d.py
peaks/core/GUI/disp_panels/disp_3d.py
peaks/core/GUI/disp_panels/disp_4d.py
peaks/core/GUI/iplot/__init__.py
peaks/core/GUI/iplot/hvplot.py
peaks/core/GUI/periodic_table/__init__.py
peaks/core/GUI/periodic_table/elements.pkl
peaks/core/GUI/periodic_table/ptab.py
peaks/core/accessors/__init__.py
peaks/core/accessors/accessor_methods.py
peaks/core/accessors/dataarray_accessors.py
peaks/core/accessors/dataset_accessors.py
peaks/core/accessors/datatree_accessors.py
peaks/core/display/__init__.py
peaks/core/display/plotting.py
peaks/core/fileIO/__init__.py
peaks/core/fileIO/data_loading.py
peaks/core/fileIO/data_saving.py
peaks/core/fileIO/helper_functions.py
peaks/core/fileIO/loc_registry.py
peaks/core/fileIO/base_arpes_data_classes/__init__.py
peaks/core/fileIO/base_arpes_data_classes/base_arpes_data_class.py
peaks/core/fileIO/base_arpes_data_classes/base_fesuma_class.py
peaks/core/fileIO/base_arpes_data_classes/base_mbs_class.py
peaks/core/fileIO/base_arpes_data_classes/base_ses_class.py
peaks/core/fileIO/base_arpes_data_classes/base_specs_class.py
peaks/core/fileIO/base_data_classes/__init__.py
peaks/core/fileIO/base_data_classes/base_data_class.py
peaks/core/fileIO/base_data_classes/base_hdf5_class.py
peaks/core/fileIO/base_data_classes/base_ibw_class.py
peaks/core/fileIO/base_data_classes/base_manipulator_class.py
peaks_arpes-0.4.4.dist-info/licenses/LICENSE.md
peaks_arpes-0.4.4.dist-info/WHEEL
peaks_arpes-0.4.4.dist-info/METADATA
peaks_arpes-0.4.4.dist-info/RECORD
