Metadata-Version: 2.4
Name: peaks-arpes
Version: 0.4.4
Summary: Python tools for analysis of angle-resolved photoemission and related spectroscopic data
Keywords: ARPES,photoemission,spectroscopy,xarray
Author: Brendan Edwards
Author-email: Phil King <pdk6@st-andrews.ac.uk>, Shu Mo <sm584@st-andrews.ac.uk>
Requires-Python: >=3.11,<3.14
Classifier: Intended Audience :: Science/Research
Classifier: License :: OSI Approved :: Apache Software License
Classifier: Programming Language :: Python :: 3
Classifier: Programming Language :: Python :: 3.11
Classifier: Programming Language :: Python :: 3.12
Classifier: Topic :: Scientific/Engineering :: Physics
License-File: LICENSE.md
Requires-Dist: ipykernel (>=6.25,<7)
Requires-Dist: ipywidgets (>=8.1,<9)
Requires-Dist: numpy (>=2.0,<3)
Requires-Dist: matplotlib (>=3.9,<4)
Requires-Dist: xarray (>=2025.6.0)
Requires-Dist: pint-xarray (>=0.4,<0.5)
Requires-Dist: dask[diagnostics] (>=2024.6.0)
Requires-Dist: h5py (>=3.11,<4)
Requires-Dist: tqdm (>=4.66,<5)
Requires-Dist: natsort (>=8.4,<9)
Requires-Dist: igor2 (>=0.5,<1)
Requires-Dist: jupyterlab (>=4.2,<5)
Requires-Dist: numbagg (>=0.8,<1)
Requires-Dist: numba-progress (>=1.1,<2)
Requires-Dist: numexpr (>=2.10, <3)
Requires-Dist: hvplot (>=0.10,<1)
Requires-Dist: pyqt6 (>=6.7,<7)
Requires-Dist: pyqtgraph (>=0.13,<1)
Requires-Dist: scikit-image (>=0.24,<1)
Requires-Dist: pyperclip (>=1.9,<2)
Requires-Dist: lmfit (>=1.3,<2)
Requires-Dist: pydantic (>=2.9,<3)
Requires-Dist: termcolor (>=2.5,<3)
Requires-Dist: h5netcdf (>=1.4,<2)
Requires-Dist: zarr (>=3.0,<4)
Requires-Dist: ruff ; extra == "dev"
Requires-Dist: pre-commit ; extra == "dev"
Requires-Dist: nbstripout ; extra == "dev"
Requires-Dist: sphinx (>=8.2,<9) ; extra == "docs"
Requires-Dist: sphinx-copybutton (>=0.5,<1) ; extra == "docs"
Requires-Dist: sphinx-togglebutton (>=0.3,<1) ; extra == "docs"
Requires-Dist: sphinx-inline-tabs (>=2023) ; extra == "docs"
Requires-Dist: sphinx-autoapi (>=3.6,<4) ; extra == "docs"
Requires-Dist: myst-parser (>=4.0,<5) ; extra == "docs"
Requires-Dist: myst-nb (>=1.2,<2) ; extra == "docs"
Requires-Dist: pydata-sphinx-theme (>=0.16,<1) ; extra == "docs"
Requires-Dist: scikit-learn (>=1.3,<2) ; extra == "ml"
Requires-Dist: ase (>3.24,<4) ; extra == "structure"
Requires-Dist: trimesh (>4.6,<5) ; extra == "structure"
Project-URL: Documentation, https://research.st-andrews.ac.uk/kinggroup/peaks/
Project-URL: Issues, https://github.com/phrgab/peaks/issues
Project-URL: Source, https://github.com/phrgab/peaks
Provides-Extra: dev
Provides-Extra: docs
Provides-Extra: ml
Provides-Extra: structure
